src/__init__.py
src/data_processing/__init__.py
src/data_processing/data_process.py
src/data_statistics/__init__.py
src/data_statistics/data_stats_for_school.py
src/data_visualization/__init__.py
src/unit_tests/__init__.py
src/unit_tests/test_data_process.py
src/unit_tests/test_data_stats_for_school.py
projekt_nypd-0.0.1.dist-info/METADATA
projekt_nypd-0.0.1.dist-info/WHEEL
projekt_nypd-0.0.1.dist-info/top_level.txt
projekt_nypd-0.0.1.dist-info/RECORD
