Metadata-Version: 2.1
Name: projekt-nypd
Version: 0.0.1
Summary: A final solution
Home-page: UNKNOWN
License: UNKNOWN
Platform: UNKNOWN
Requires-Python: >=3.8
